{
  "section":"1-211",
  "rows":{
    "1":[
      "1",
      "2",
      "3",
      "4",
      "5"
    ],
    "2":[
      "6",
      "7",
      "8",
      "9",
      "10"
    ]
  },
  "seats":[
    {
      "id":"GEWTEMJRHIYTUNI",
      "section":"1-211",
      "row":"1",
      "seat":"5",
      "xN":0.6048837890625001,
      "yN":0.7760416666666666
    },
    {
      "id":"GEWTEMJRHIYTUNA",
      "section":"1-211",
      "row":"1",
      "seat":"4",
      "xN":0.6082041015625,
      "yN":0.7760416666666666
    },
    {
      "id":"GEWTEMJRHIYTUMY",
      "section":"1-211",
      "row":"1",
      "seat":"3",
      "xN":0.6098642578125,
      "yN":0.7760416666666666
    },
    {
      "id":"GEWTEMJRHIYTUMQ",
      "section":"1-211",
      "row":"1",
      "seat":"2",
      "xN":0.6115244140625,
      "yN":0.7760416666666666
    },
    {
      "id":"GEWTEMJRHIYTUMI",
      "section":"1-211",
      "row":"1",
      "seat":"1",
      "xN":0.6131845703125001,
      "yN":0.7760416666666666
    },
    {
      "id":"GEWTEMJRHIZDUMJQ",
      "section":"1-211",
      "row":"2",
      "seat":"10",
      "xN":0.6050068359375,
      "yN":0.7794921875
    },
    {
      "id":"GEWTEMJRHIZDUOI",
      "section":"1-211",
      "row":"2",
      "seat":"9",
      "xN":0.6083271484375,
      "yN":0.7794921875
    },
    {
      "id":"GEWTEMJRHIZDUOA",
      "section":"1-211",
      "row":"2",
      "seat":"8",
      "xN":0.6099873046875001,
      "yN":0.7794921875
    },
    {
      "id":"GEWTEMJRHIZDUNY",
      "section":"1-211",
      "row":"2",
      "seat":"7",
      "xN":0.6116474609375,
      "yN":0.7794921875
    },
    {
      "id":"GEWTEMJRHIZDUNQ",
      "section":"1-211",
      "row":"2",
      "seat":"6",
      "xN":0.6133076171875,
      "yN":0.7794921875
    }
  ]
}