{
  "section":"1-323",
  "rows":{
    "1":[
      "1",
      "2",
      "3",
      "4",
      "5"
    ],
    "2":[
      "6",
      "7",
      "8",
      "9",
      "10"
    ]
  },
  "seats":[
    {
      "id":"GEWTGMRTHIYTUNI",
      "section":"1-323",
      "row":"1",
      "seat":"5",
      "xN":0.3549052734375,
      "yN":0.7900625
    },
    {
      "id":"GEWTGMRTHIYTUNA",
      "section":"1-323",
      "row":"1",
      "seat":"4",
      "xN":0.35645800781250003,
      "yN":0.7900625
    },
    {
      "id":"GEWTGMRTHIYTUMY",
      "section":"1-323",
      "row":"1",
      "seat":"3",
      "xN":0.3580107421875,
      "yN":0.7900625
    },
    {
      "id":"GEWTGMRTHIYTUMQ",
      "section":"1-323",
      "row":"1",
      "seat":"2",
      "xN":0.3595634765625,
      "yN":0.7900625
    },
    {
      "id":"GEWTGMRTHIYTUMI",
      "section":"1-323",
      "row":"1",
      "seat":"1",
      "xN":0.3611162109375,
      "yN":0.7900625
    },
    {
      "id":"GEWTGMRTHIZDUMJQ",
      "section":"1-323",
      "row":"2",
      "seat":"10",
      "xN":0.3549052734375,
      "yN":0.7935130208333334
    },
    {
      "id":"GEWTGMRTHIZDUOI",
      "section":"1-323",
      "row":"2",
      "seat":"9",
      "xN":0.35645800781250003,
      "yN":0.7935130208333334
    },
    {
      "id":"GEWTGMRTHIZDUOA",
      "section":"1-323",
      "row":"2",
      "seat":"8",
      "xN":0.3580107421875,
      "yN":0.7935130208333334
    },
    {
      "id":"GEWTGMRTHIZDUNY",
      "section":"1-323",
      "row":"2",
      "seat":"7",
      "xN":0.3595634765625,
      "yN":0.7935130208333334
    },
    {
      "id":"GEWTGMRTHIZDUNQ",
      "section":"1-323",
      "row":"2",
      "seat":"6",
      "xN":0.3611162109375,
      "yN":0.7935130208333334
    }
  ]
}