{
  "section":"1-322",
  "rows":{
    "1":[
      "1",
      "2",
      "3",
      "4",
      "5"
    ],
    "2":[
      "6",
      "7",
      "8",
      "9",
      "10"
    ]
  },
  "seats":[
    {
      "id":"GEWTGMRSHIYTUNI",
      "section":"1-322",
      "row":"1",
      "seat":"5",
      "xN":0.3657744140625,
      "yN":0.7900625
    },
    {
      "id":"GEWTGMRSHIYTUNA",
      "section":"1-322",
      "row":"1",
      "seat":"4",
      "xN":0.3673271484375,
      "yN":0.7900625
    },
    {
      "id":"GEWTGMRSHIYTUMY",
      "section":"1-322",
      "row":"1",
      "seat":"3",
      "xN":0.3688798828125,
      "yN":0.7900625
    },
    {
      "id":"GEWTGMRSHIYTUMQ",
      "section":"1-322",
      "row":"1",
      "seat":"2",
      "xN":0.3704326171875,
      "yN":0.7900625
    },
    {
      "id":"GEWTGMRSHIYTUMI",
      "section":"1-322",
      "row":"1",
      "seat":"1",
      "xN":0.3719853515625,
      "yN":0.7900625
    },
    {
      "id":"GEWTGMRSHIZDUMJQ",
      "section":"1-322",
      "row":"2",
      "seat":"10",
      "xN":0.3657744140625,
      "yN":0.7935130208333334
    },
    {
      "id":"GEWTGMRSHIZDUOI",
      "section":"1-322",
      "row":"2",
      "seat":"9",
      "xN":0.3673271484375,
      "yN":0.7935130208333334
    },
    {
      "id":"GEWTGMRSHIZDUOA",
      "section":"1-322",
      "row":"2",
      "seat":"8",
      "xN":0.3688798828125,
      "yN":0.7935130208333334
    },
    {
      "id":"GEWTGMRSHIZDUNY",
      "section":"1-322",
      "row":"2",
      "seat":"7",
      "xN":0.3704326171875,
      "yN":0.7935130208333334
    },
    {
      "id":"GEWTGMRSHIZDUNQ",
      "section":"1-322",
      "row":"2",
      "seat":"6",
      "xN":0.3719853515625,
      "yN":0.7935130208333334
    }
  ]
}